{
	"id": "40f44bf4-aa35-591a-bc4b-d7309a77c866",
	"name": "萤石云API",
	"description": "",
	"order": [
		"b137ff85-cea2-309a-0f4d-6fbb39b16087",
		"0b6b2e0b-a265-2110-4294-1cdbf45e4f99",
		"d9265a8a-8345-4da9-ce0a-24f993f6fe4e",
		"2d0936c3-983e-db10-47a5-84ccd5bbd3eb",
		"578ea598-dbf1-60d1-8091-bb334e118db6",
		"00203017-16ef-cc2a-a401-bfffbe647bc4",
		"626f3169-779f-a6d7-5037-3503bcd1c6ad",
		"e04e05b8-105a-5bef-f1a0-9b1ac563bd01",
		"b57c6e7e-b9fe-5501-fd7a-7176aad5cf17",
		"7bec18ee-7f7e-937b-3395-7f11fbe2e99a",
		"e8471132-9823-bc1f-1959-69658df18a07",
		"465b63fa-361e-bd1d-6d6e-379a0b7a01c0",
		"f783d822-a1fd-e552-1cae-d1616886eda9",
		"b69a19ae-571f-19b2-8d61-5bd7d38bbdd1",
		"2cfd911d-0710-f863-8806-7da280cb6238",
		"f980589a-df36-3146-b9d6-7a03c404d8d6",
		"d3ffa412-6ce9-2aea-adfd-9096cfe6e1cc",
		"23b94680-0a6d-7fc2-ae1d-586a70039b86",
		"101d6747-ee4c-403e-f691-aaa6b0c2f1e2",
		"1010a0ae-b9c4-a3f5-7857-41fe6f6a460a",
		"fd69ece9-aec9-a391-0856-0f223b92d88f",
		"fa190de9-a69e-bf72-389c-fc5643d94cf1",
		"9c93878d-009e-5a2b-6b80-d98f46a91fbf",
		"abdc33bd-4c1e-fda7-dcd1-0e591743a7ea",
		"5c8caa21-7306-0354-12c6-af76730a6996"
	],
	"folders": [],
	"timestamp": 1500427792135,
	"owner": "2399702",
	"public": false,
	"requests": [
		{
			"id": "00203017-16ef-cc2a-a401-bfffbe647bc4",
			"headers": "Content-Type: application/x-www-form-urlencoded\n",
			"headerData": [
				{
					"key": "Content-Type",
					"value": "application/x-www-form-urlencoded",
					"description": "",
					"enabled": true
				}
			],
			"url": "https://open.ys7.com/api/lapp/device/name/update",
			"queryParams": [],
			"preRequestScript": null,
			"pathVariables": {},
			"pathVariableData": [],
			"method": "POST",
			"data": [
				{
					"key": "accessToken",
					"value": "at.b4nuxgd79t1ut32620c8ug07499gc7tg-707f26o0hi-1xdy0o3-n4puiftrn",
					"description": "",
					"type": "text",
					"enabled": true
				},
				{
					"key": "deviceSerial",
					"value": "795616110",
					"description": "",
					"type": "text",
					"enabled": true
				},
				{
					"key": "deviceName",
					"value": "A1C-zencloud",
					"description": "",
					"type": "text",
					"enabled": true
				}
			],
			"dataMode": "urlencoded",
			"tests": null,
			"currentHelper": "normal",
			"helperAttributes": {},
			"time": 1500875131184,
			"name": "修改设备名",
			"description": "",
			"collectionId": "40f44bf4-aa35-591a-bc4b-d7309a77c866",
			"responses": []
		},
		{
			"id": "0b6b2e0b-a265-2110-4294-1cdbf45e4f99",
			"headers": "Content-Type: application/x-www-form-urlencoded\n",
			"headerData": [
				{
					"key": "Content-Type",
					"value": "application/x-www-form-urlencoded",
					"description": "",
					"enabled": true
				}
			],
			"url": "https://open.ys7.com/api/lapp/token/get",
			"queryParams": [],
			"preRequestScript": null,
			"pathVariables": {},
			"pathVariableData": [],
			"method": "POST",
			"data": [
				{
					"key": "appKey",
					"value": "3ae748f148cc4004b9f3dfb272e25c77",
					"type": "text",
					"enabled": true,
					"description": ""
				},
				{
					"key": "appSecret",
					"value": "525705978753c65c6e8170f2dfec5856",
					"type": "text",
					"enabled": true,
					"description": ""
				},
				{
					"key": "accessToken",
					"value": "at.3egi1pujd1gogblqbnloo3nr3th7fs0k-707eveuodc-0y24n2d-ko7sjyg2o",
					"type": "text",
					"enabled": false,
					"description": ""
				},
				{
					"key": "deviceSerial",
					"value": "427734888",
					"type": "text",
					"enabled": false,
					"description": ""
				},
				{
					"key": "validateCode",
					"value": "ABCDEF",
					"type": "text",
					"enabled": false,
					"description": ""
				}
			],
			"dataMode": "urlencoded",
			"version": 2,
			"tests": null,
			"currentHelper": "normal",
			"helperAttributes": {},
			"time": 1500875007601,
			"name": "accessToken获取",
			"description": "",
			"collectionId": "40f44bf4-aa35-591a-bc4b-d7309a77c866",
			"responses": []
		},
		{
			"id": "1010a0ae-b9c4-a3f5-7857-41fe6f6a460a",
			"headers": "Content-Type: application/x-www-form-urlencoded\n",
			"headerData": [
				{
					"key": "Content-Type",
					"value": "application/x-www-form-urlencoded",
					"description": "",
					"enabled": true
				}
			],
			"url": "https://open.ys7.com/api/lapp/detector/status/set",
			"queryParams": [],
			"preRequestScript": null,
			"pathVariables": {},
			"pathVariableData": [],
			"method": "POST",
			"data": [
				{
					"key": "accessToken",
					"value": "at.b4nuxgd79t1ut32620c8ug07499gc7tg-707f26o0hi-1xdy0o3-n4puiftrn",
					"description": "",
					"type": "text",
					"enabled": true
				},
				{
					"key": "deviceSerial",
					"value": "795616110",
					"description": "",
					"type": "text",
					"enabled": true
				},
				{
					"key": "detectorSerial",
					"value": "794131206",
					"description": "探测器序列号",
					"type": "text",
					"enabled": true
				},
				{
					"key": "safeMode",
					"value": "0",
					"description": "安全模式：0-在家，1-外出，2-睡眠",
					"type": "text",
					"enabled": true
				},
				{
					"key": "enable",
					"value": "0",
					"description": "状态：0-关闭，1-开启",
					"type": "text",
					"enabled": true
				}
			],
			"dataMode": "urlencoded",
			"tests": null,
			"currentHelper": "normal",
			"helperAttributes": {},
			"time": 1500879256074,
			"name": "设置探测器状态",
			"description": "",
			"collectionId": "40f44bf4-aa35-591a-bc4b-d7309a77c866",
			"responses": []
		},
		{
			"id": "101d6747-ee4c-403e-f691-aaa6b0c2f1e2",
			"headers": "Content-Type: application/x-www-form-urlencoded\n",
			"headerData": [
				{
					"key": "Content-Type",
					"value": "application/x-www-form-urlencoded",
					"description": "",
					"enabled": true
				}
			],
			"url": "https://open.ys7.com/api/lapp/detector/list",
			"queryParams": [],
			"pathVariables": {},
			"pathVariableData": [],
			"preRequestScript": null,
			"method": "POST",
			"collectionId": "40f44bf4-aa35-591a-bc4b-d7309a77c866",
			"data": [
				{
					"key": "accessToken",
					"value": "at.b4nuxgd79t1ut32620c8ug07499gc7tg-707f26o0hi-1xdy0o3-n4puiftrn",
					"description": "",
					"type": "text",
					"enabled": true
				},
				{
					"key": "deviceSerial",
					"value": "795616110",
					"description": "",
					"type": "text",
					"enabled": true
				}
			],
			"dataMode": "urlencoded",
			"name": "获取探测器列表",
			"description": "",
			"descriptionFormat": "html",
			"time": 1500877746468,
			"version": 2,
			"responses": [],
			"tests": null,
			"currentHelper": "normal",
			"helperAttributes": {}
		},
		{
			"id": "23b94680-0a6d-7fc2-ae1d-586a70039b86",
			"headers": "Content-Type: application/x-www-form-urlencoded\n",
			"headerData": [
				{
					"key": "Content-Type",
					"value": "application/x-www-form-urlencoded",
					"description": "",
					"enabled": true
				}
			],
			"url": "https://open.ys7.com/api/lapp/alarm/device/list",
			"queryParams": [],
			"preRequestScript": null,
			"pathVariables": {},
			"pathVariableData": [],
			"method": "POST",
			"data": [
				{
					"key": "accessToken",
					"value": "at.b4nuxgd79t1ut32620c8ug07499gc7tg-707f26o0hi-1xdy0o3-n4puiftrn",
					"description": "",
					"type": "text",
					"enabled": true
				},
				{
					"key": "deviceSerial",
					"value": "795616110",
					"description": "",
					"type": "text",
					"enabled": true
				},
				{
					"key": "pageSize",
					"value": "",
					"description": "分页大小，默认为10，最大为,50",
					"type": "text",
					"enabled": true
				},
				{
					"key": "pageStart",
					"value": "",
					"description": "分页起始页，从0开始",
					"type": "text",
					"enabled": true
				},
				{
					"key": "startTime",
					"value": "",
					"description": "报警查询开始时间，时间格式为1457420564508，精确到毫秒，默认为今日0点，最多查询当前时间起前推7天以内的数据",
					"type": "text",
					"enabled": true
				},
				{
					"key": "endTime",
					"value": "",
					"description": "报警查询结束时间，时间格式为1457420771029，默认为当前时间",
					"type": "text",
					"enabled": true
				},
				{
					"key": "status",
					"value": "2",
					"description": "报警消息状态：2-所有，1-已读，0-未读，默认为0（未读状态）",
					"type": "text",
					"enabled": true
				},
				{
					"key": "alarmType",
					"value": "",
					"description": "报警类型，默认为-1（全部）",
					"type": "text",
					"enabled": true
				}
			],
			"dataMode": "urlencoded",
			"tests": null,
			"currentHelper": "normal",
			"helperAttributes": {},
			"time": 1500879259307,
			"name": "按照设备获取报警消息列表",
			"description": "",
			"collectionId": "40f44bf4-aa35-591a-bc4b-d7309a77c866",
			"responses": []
		},
		{
			"id": "2cfd911d-0710-f863-8806-7da280cb6238",
			"headers": "Content-Type: application/x-www-form-urlencoded\n",
			"headerData": [
				{
					"key": "Content-Type",
					"value": "application/x-www-form-urlencoded",
					"description": "",
					"enabled": true
				}
			],
			"url": "https://open.ys7.com/api/lapp/device/version/info",
			"queryParams": [],
			"pathVariables": {},
			"pathVariableData": [],
			"preRequestScript": null,
			"method": "POST",
			"collectionId": "40f44bf4-aa35-591a-bc4b-d7309a77c866",
			"data": [
				{
					"key": "accessToken",
					"value": "at.b4nuxgd79t1ut32620c8ug07499gc7tg-707f26o0hi-1xdy0o3-n4puiftrn",
					"description": "",
					"type": "text",
					"enabled": true
				},
				{
					"key": "deviceSerial",
					"value": "795616110",
					"description": "",
					"type": "text",
					"enabled": true
				}
			],
			"dataMode": "urlencoded",
			"name": "获取设备版本信息",
			"description": "",
			"descriptionFormat": "html",
			"time": 1500876565113,
			"version": 2,
			"responses": [],
			"tests": null,
			"currentHelper": "normal",
			"helperAttributes": {}
		},
		{
			"id": "2d0936c3-983e-db10-47a5-84ccd5bbd3eb",
			"headers": "Content-Type: application/x-www-form-urlencoded\n",
			"headerData": [
				{
					"key": "",
					"value": "",
					"description": "",
					"enabled": true
				},
				{
					"key": "Content-Type",
					"value": "application/x-www-form-urlencoded",
					"description": "",
					"enabled": true
				}
			],
			"url": "https://open.ys7.com/api/lapp/alarm/list",
			"queryParams": [],
			"preRequestScript": null,
			"pathVariables": {},
			"pathVariableData": [],
			"method": "POST",
			"data": [
				{
					"key": "accessToken",
					"value": "at.b4nuxgd79t1ut32620c8ug07499gc7tg-707f26o0hi-1xdy0o3-n4puiftrn",
					"description": "",
					"type": "text",
					"enabled": true
				},
				{
					"key": "startTime",
					"value": "",
					"description": "",
					"type": "text",
					"enabled": true
				},
				{
					"key": "endTime",
					"value": "",
					"description": "",
					"type": "text",
					"enabled": true
				},
				{
					"key": "alarmType",
					"value": "",
					"description": "",
					"type": "text",
					"enabled": true
				},
				{
					"key": "status",
					"value": "2",
					"description": "",
					"type": "text",
					"enabled": true
				},
				{
					"key": "pageStart",
					"value": "0",
					"description": "",
					"type": "text",
					"enabled": true
				},
				{
					"key": "pageSize",
					"value": "",
					"description": "",
					"type": "text",
					"enabled": true
				}
			],
			"dataMode": "urlencoded",
			"version": 2,
			"tests": null,
			"currentHelper": "normal",
			"helperAttributes": {},
			"time": 1500878235335,
			"name": "获取报警信息列表",
			"description": "",
			"collectionId": "40f44bf4-aa35-591a-bc4b-d7309a77c866",
			"responses": []
		},
		{
			"id": "465b63fa-361e-bd1d-6d6e-379a0b7a01c0",
			"headers": "Content-Type: application/x-www-form-urlencoded\n",
			"headerData": [
				{
					"key": "Content-Type",
					"value": "application/x-www-form-urlencoded",
					"description": "",
					"enabled": true
				}
			],
			"url": "https://open.ys7.com/api/lapp/device/sound/switch/status",
			"queryParams": [],
			"pathVariables": {},
			"pathVariableData": [],
			"preRequestScript": null,
			"method": "POST",
			"collectionId": "40f44bf4-aa35-591a-bc4b-d7309a77c866",
			"data": [
				{
					"key": "accessToken",
					"value": "at.b4nuxgd79t1ut32620c8ug07499gc7tg-707f26o0hi-1xdy0o3-n4puiftrn",
					"description": "",
					"type": "text",
					"enabled": true
				},
				{
					"key": "deviceSerial",
					"value": "795616110",
					"description": "",
					"type": "text",
					"enabled": true
				}
			],
			"dataMode": "urlencoded",
			"name": "获取wifi配置提示音开关状态",
			"description": "",
			"descriptionFormat": "html",
			"time": 1500875243841,
			"version": 2,
			"responses": [],
			"tests": null,
			"currentHelper": "normal",
			"helperAttributes": {}
		},
		{
			"id": "578ea598-dbf1-60d1-8091-bb334e118db6",
			"headers": "Content-Type: application/x-www-form-urlencoded\n",
			"headerData": [
				{
					"key": "Content-Type",
					"value": "application/x-www-form-urlencoded",
					"description": "",
					"enabled": true
				}
			],
			"url": "https://open.ys7.com/api/lapp/device/delete",
			"queryParams": [],
			"pathVariables": {},
			"pathVariableData": [],
			"preRequestScript": null,
			"method": "POST",
			"collectionId": "40f44bf4-aa35-591a-bc4b-d7309a77c866",
			"data": [
				{
					"key": "accessToken",
					"value": "at.b4nuxgd79t1ut32620c8ug07499gc7tg-707f26o0hi-1xdy0o3-n4puiftrn",
					"description": "",
					"type": "text",
					"enabled": true
				},
				{
					"key": "deviceSerial",
					"value": "795616111",
					"description": "",
					"type": "text",
					"enabled": true
				}
			],
			"dataMode": "urlencoded",
			"name": "删除设备",
			"description": "",
			"descriptionFormat": "html",
			"time": 1500869751219,
			"version": 2,
			"responses": [],
			"tests": null,
			"currentHelper": "normal",
			"helperAttributes": {}
		},
		{
			"id": "5c8caa21-7306-0354-12c6-af76730a6996",
			"headers": "Content-Type: application/x-www-form-urlencoded\n",
			"headerData": [
				{
					"key": "Content-Type",
					"value": "application/x-www-form-urlencoded",
					"description": "",
					"enabled": true
				}
			],
			"url": "https://open.ys7.com/api/lapp/cloud/storage/device/info",
			"queryParams": [],
			"preRequestScript": null,
			"pathVariables": {},
			"pathVariableData": [],
			"method": "POST",
			"data": [
				{
					"key": "accessToken",
					"value": "at.b4nuxgd79t1ut32620c8ug07499gc7tg-707f26o0hi-1xdy0o3-n4puiftrn",
					"description": "",
					"type": "text",
					"enabled": true
				},
				{
					"key": "deviceSerial",
					"value": "795616110",
					"description": "",
					"type": "text",
					"enabled": true
				},
				{
					"key": "phone",
					"value": "18109692808",
					"description": "",
					"type": "text",
					"enabled": true
				},
				{
					"key": "channelNo",
					"value": "",
					"description": "非必选参数，不为空表示查询指定通道云存储信息，为空表示查询设备本身云存储信息，默认是1",
					"type": "text",
					"enabled": true
				}
			],
			"dataMode": "urlencoded",
			"tests": null,
			"currentHelper": "normal",
			"helperAttributes": {},
			"time": 1500879248667,
			"name": "查询设备云存储信息",
			"description": "",
			"collectionId": "40f44bf4-aa35-591a-bc4b-d7309a77c866",
			"responses": []
		},
		{
			"id": "626f3169-779f-a6d7-5037-3503bcd1c6ad",
			"headers": "Content-Type: application/x-www-form-urlencoded\n",
			"headerData": [
				{
					"key": "Content-Type",
					"value": "application/x-www-form-urlencoded",
					"description": "",
					"enabled": true
				}
			],
			"url": "https://open.ys7.com/api/lapp/device/ipc/add",
			"queryParams": [],
			"preRequestScript": null,
			"pathVariables": {},
			"pathVariableData": [],
			"method": "POST",
			"data": [
				{
					"key": "accessToken",
					"value": "at.b4nuxgd79t1ut32620c8ug07499gc7tg-707f26o0hi-1xdy0o3-n4puiftrn",
					"description": "",
					"type": "text",
					"enabled": true
				},
				{
					"key": "deviceSerial",
					"value": "795616110",
					"description": "",
					"type": "text",
					"enabled": true
				},
				{
					"key": "ipcSerial",
					"value": "795616111",
					"description": "待关联的IPC设备序列号",
					"type": "text",
					"enabled": true
				}
			],
			"dataMode": "urlencoded",
			"tests": null,
			"currentHelper": "normal",
			"helperAttributes": {},
			"time": 1500875128593,
			"name": "NVR设备关联IPC",
			"description": "",
			"collectionId": "40f44bf4-aa35-591a-bc4b-d7309a77c866",
			"responses": []
		},
		{
			"id": "7bec18ee-7f7e-937b-3395-7f11fbe2e99a",
			"headers": "Content-Type: application/x-www-form-urlencoded\n",
			"headerData": [
				{
					"key": "Content-Type",
					"value": "application/x-www-form-urlencoded",
					"description": "",
					"enabled": true
				}
			],
			"url": "https://open.ys7.com/api/lapp/device/list",
			"queryParams": [],
			"pathVariables": {},
			"pathVariableData": [],
			"preRequestScript": null,
			"method": "POST",
			"collectionId": "40f44bf4-aa35-591a-bc4b-d7309a77c866",
			"data": [
				{
					"key": "accessToken",
					"value": "at.b4nuxgd79t1ut32620c8ug07499gc7tg-707f26o0hi-1xdy0o3-n4puiftrn",
					"description": "",
					"type": "text",
					"enabled": true
				},
				{
					"key": "pageStart",
					"value": "0",
					"description": "",
					"type": "text",
					"enabled": true
				},
				{
					"key": "pageSize",
					"value": "2",
					"description": "",
					"type": "text",
					"enabled": true
				}
			],
			"dataMode": "params",
			"name": "获取设备列表",
			"description": "",
			"descriptionFormat": "html",
			"time": 1500427792135,
			"version": 2,
			"responses": [],
			"tests": null,
			"currentHelper": "normal",
			"helperAttributes": {}
		},
		{
			"id": "9c93878d-009e-5a2b-6b80-d98f46a91fbf",
			"headers": "Content-Type: application/x-www-form-urlencoded\n",
			"headerData": [
				{
					"key": "Content-Type",
					"value": "application/x-www-form-urlencoded",
					"description": "",
					"enabled": true
				}
			],
			"url": "https://open.ys7.com/api/lapp/detector/cancelAlarm",
			"queryParams": [],
			"preRequestScript": null,
			"pathVariables": {},
			"pathVariableData": [],
			"method": "POST",
			"data": [
				{
					"key": "accessToken",
					"value": "at.b4nuxgd79t1ut32620c8ug07499gc7tg-707f26o0hi-1xdy0o3-n4puiftrn",
					"description": "",
					"type": "text",
					"enabled": true
				},
				{
					"key": "deviceSerial",
					"value": "795616110",
					"description": "",
					"type": "text",
					"enabled": true
				}
			],
			"dataMode": "urlencoded",
			"tests": null,
			"currentHelper": "normal",
			"helperAttributes": {},
			"time": 1500879251154,
			"name": "设备一键消警",
			"description": "",
			"collectionId": "40f44bf4-aa35-591a-bc4b-d7309a77c866",
			"responses": []
		},
		{
			"id": "abdc33bd-4c1e-fda7-dcd1-0e591743a7ea",
			"headers": "Content-Type: application/x-www-form-urlencoded\n",
			"headerData": [
				{
					"key": "Content-Type",
					"value": "application/x-www-form-urlencoded",
					"description": "",
					"enabled": true
				}
			],
			"url": "https://open.ys7.com/api/lapp/passengerflow/switch/status",
			"queryParams": [],
			"preRequestScript": null,
			"pathVariables": {},
			"pathVariableData": [],
			"method": "POST",
			"data": [
				{
					"key": "accessToken",
					"value": "at.b4nuxgd79t1ut32620c8ug07499gc7tg-707f26o0hi-1xdy0o3-n4puiftrn",
					"description": "",
					"type": "text",
					"enabled": true
				},
				{
					"key": "deviceSerial",
					"value": "795616110",
					"description": "",
					"type": "text",
					"enabled": true
				}
			],
			"dataMode": "urlencoded",
			"tests": null,
			"currentHelper": "normal",
			"helperAttributes": {},
			"time": 1500879092930,
			"name": "获取客流统计开关状态",
			"description": "",
			"collectionId": "40f44bf4-aa35-591a-bc4b-d7309a77c866",
			"responses": []
		},
		{
			"id": "b137ff85-cea2-309a-0f4d-6fbb39b16087",
			"headers": "Content-Type: application/x-www-form-urlencoded\n",
			"headerData": [
				{
					"key": "Content-Type",
					"value": "application/x-www-form-urlencoded",
					"description": "",
					"enabled": true
				}
			],
			"url": "https://open.ys7.com/api/lapp/device/add",
			"queryParams": [],
			"preRequestScript": null,
			"pathVariables": {},
			"pathVariableData": [],
			"method": "POST",
			"data": [],
			"dataMode": "raw",
			"version": 2,
			"tests": null,
			"currentHelper": "normal",
			"helperAttributes": {},
			"time": 1500875134233,
			"name": "设备添加",
			"description": "",
			"collectionId": "40f44bf4-aa35-591a-bc4b-d7309a77c866",
			"responses": [],
			"rawModeData": ""
		},
		{
			"id": "b57c6e7e-b9fe-5501-fd7a-7176aad5cf17",
			"headers": "Content-Type: application/x-www-form-urlencoded\n",
			"headerData": [
				{
					"key": "Content-Type",
					"value": "application/x-www-form-urlencoded",
					"description": "",
					"enabled": true
				}
			],
			"url": "https://open.ys7.com/api/lapp/device/defence/set",
			"queryParams": [],
			"preRequestScript": null,
			"pathVariables": {},
			"pathVariableData": [],
			"method": "POST",
			"data": [
				{
					"key": "accessToken",
					"value": "at.b4nuxgd79t1ut32620c8ug07499gc7tg-707f26o0hi-1xdy0o3-n4puiftrn",
					"description": "",
					"type": "text",
					"enabled": true
				},
				{
					"key": "deviceSerial",
					"value": "795616110",
					"description": "",
					"type": "text",
					"enabled": true
				},
				{
					"key": "isDefence",
					"value": "8",
					"description": "",
					"type": "text",
					"enabled": true
				}
			],
			"dataMode": "urlencoded",
			"tests": null,
			"currentHelper": "normal",
			"helperAttributes": {},
			"time": 1500875092465,
			"name": "设备布撤防",
			"description": "",
			"collectionId": "40f44bf4-aa35-591a-bc4b-d7309a77c866",
			"responses": []
		},
		{
			"id": "b69a19ae-571f-19b2-8d61-5bd7d38bbdd1",
			"headers": "Content-Type: application/x-www-form-urlencoded\n",
			"headerData": [
				{
					"key": "Content-Type",
					"value": "application/x-www-form-urlencoded",
					"description": "",
					"enabled": true
				}
			],
			"url": "https://open.ys7.com/api/lapp/device/notify/switch",
			"queryParams": [],
			"preRequestScript": null,
			"pathVariables": {},
			"pathVariableData": [],
			"method": "POST",
			"data": [
				{
					"key": "accessToken",
					"value": "at.b4nuxgd79t1ut32620c8ug07499gc7tg-707f26o0hi-1xdy0o3-n4puiftrn",
					"description": "",
					"type": "text",
					"enabled": true
				},
				{
					"key": "deviceSerial",
					"value": "795616110",
					"description": "",
					"type": "text",
					"enabled": true
				},
				{
					"key": "enable",
					"value": "1",
					"description": "",
					"type": "text",
					"enabled": true
				}
			],
			"dataMode": "urlencoded",
			"tests": null,
			"currentHelper": "normal",
			"helperAttributes": {},
			"time": 1500877789001,
			"name": "开启或关闭设备下线通知",
			"description": "",
			"collectionId": "40f44bf4-aa35-591a-bc4b-d7309a77c866",
			"responses": []
		},
		{
			"id": "d3ffa412-6ce9-2aea-adfd-9096cfe6e1cc",
			"headers": "Content-Type: application/x-www-form-urlencoded\n",
			"headerData": [
				{
					"key": "Content-Type",
					"value": "application/x-www-form-urlencoded",
					"description": "",
					"enabled": true
				}
			],
			"url": "https://open.ys7.com/api/lapp/device/upgrade/status",
			"queryParams": [],
			"pathVariables": {},
			"pathVariableData": [],
			"preRequestScript": null,
			"method": "POST",
			"collectionId": "40f44bf4-aa35-591a-bc4b-d7309a77c866",
			"data": [
				{
					"key": "accessToken",
					"value": "at.b4nuxgd79t1ut32620c8ug07499gc7tg-707f26o0hi-1xdy0o3-n4puiftrn",
					"description": "",
					"type": "text",
					"enabled": true
				},
				{
					"key": "deviceSerial",
					"value": "795616110",
					"description": "0-正在升级，1-设备重启，2-升级成功，3-升级失败",
					"type": "text",
					"enabled": true
				}
			],
			"dataMode": "urlencoded",
			"name": "获取设备升级状态",
			"description": "",
			"descriptionFormat": "html",
			"time": 1500876783488,
			"version": 2,
			"responses": [],
			"tests": null,
			"currentHelper": "normal",
			"helperAttributes": {}
		},
		{
			"id": "d9265a8a-8345-4da9-ce0a-24f993f6fe4e",
			"headers": "Content-Type: application/x-www-form-urlencoded\n",
			"headerData": [
				{
					"key": "Content-Type",
					"value": "application/x-www-form-urlencoded",
					"description": "",
					"enabled": true
				}
			],
			"url": "https://open.ys7.com/api/lapp/camera/list",
			"queryParams": [],
			"pathVariables": {},
			"pathVariableData": [],
			"preRequestScript": null,
			"method": "POST",
			"collectionId": "40f44bf4-aa35-591a-bc4b-d7309a77c866",
			"data": [
				{
					"key": "accessToken",
					"value": "at.b4nuxgd79t1ut32620c8ug07499gc7tg-707f26o0hi-1xdy0o3-n4puiftrn",
					"description": "",
					"type": "text",
					"enabled": true
				},
				{
					"key": "pageStart",
					"value": "0",
					"description": "",
					"type": "text",
					"enabled": true
				},
				{
					"key": "pageSize",
					"value": "2",
					"description": "",
					"type": "text",
					"enabled": true
				}
			],
			"dataMode": "urlencoded",
			"name": "获取摄像头列表",
			"description": "",
			"descriptionFormat": "html",
			"time": 1500599165741,
			"version": 2,
			"responses": [],
			"tests": null,
			"currentHelper": "normal",
			"helperAttributes": {}
		},
		{
			"id": "e04e05b8-105a-5bef-f1a0-9b1ac563bd01",
			"headers": "Content-Type: application/x-www-form-urlencoded\n",
			"headerData": [
				{
					"key": "Content-Type",
					"value": "application/x-www-form-urlencoded",
					"description": "",
					"enabled": true
				}
			],
			"url": "https://open.ys7.com/api/lapp/device/ipc/delete",
			"queryParams": [],
			"pathVariables": {},
			"pathVariableData": [],
			"preRequestScript": null,
			"method": "POST",
			"collectionId": "40f44bf4-aa35-591a-bc4b-d7309a77c866",
			"data": [
				{
					"key": "accessToken",
					"value": "at.b4nuxgd79t1ut32620c8ug07499gc7tg-707f26o0hi-1xdy0o3-n4puiftrn",
					"description": "",
					"type": "text",
					"enabled": true
				},
				{
					"key": "deviceSerial",
					"value": "795616110",
					"description": "",
					"type": "text",
					"enabled": true
				},
				{
					"key": "ipcSerial",
					"value": "797761167",
					"description": "",
					"type": "text",
					"enabled": true
				}
			],
			"dataMode": "urlencoded",
			"name": "NVR设备删除IPC",
			"description": "",
			"descriptionFormat": "html",
			"time": 1500873582643,
			"version": 2,
			"responses": [],
			"tests": null,
			"currentHelper": "normal",
			"helperAttributes": {}
		},
		{
			"id": "e8471132-9823-bc1f-1959-69658df18a07",
			"headers": "Content-Type: application/x-www-form-urlencoded\n",
			"headerData": [
				{
					"key": "Content-Type",
					"value": "application/x-www-form-urlencoded",
					"description": "",
					"enabled": true
				}
			],
			"url": "https://open.ys7.com/api/lapp/device/info",
			"queryParams": [],
			"preRequestScript": null,
			"pathVariables": {},
			"pathVariableData": [],
			"method": "POST",
			"data": [
				{
					"key": "accessToken",
					"value": "at.b4nuxgd79t1ut32620c8ug07499gc7tg-707f26o0hi-1xdy0o3-n4puiftrn",
					"description": "",
					"type": "text",
					"enabled": true
				},
				{
					"key": "deviceSerial",
					"value": "795616110",
					"description": "",
					"type": "text",
					"enabled": true
				}
			],
			"dataMode": "urlencoded",
			"tests": null,
			"currentHelper": "normal",
			"helperAttributes": {},
			"time": 1500875121769,
			"name": "获取单个设备信息",
			"description": "",
			"collectionId": "40f44bf4-aa35-591a-bc4b-d7309a77c866",
			"responses": []
		},
		{
			"id": "f783d822-a1fd-e552-1cae-d1616886eda9",
			"headers": "Content-Type: application/x-www-form-urlencoded\n",
			"headerData": [
				{
					"key": "Content-Type",
					"value": "application/x-www-form-urlencoded",
					"description": "",
					"enabled": true
				}
			],
			"url": "https://open.ys7.com/api/lapp/device/alarm/sound/set",
			"queryParams": [],
			"preRequestScript": null,
			"pathVariables": {},
			"pathVariableData": [],
			"method": "POST",
			"data": [
				{
					"key": "accessToken",
					"value": "at.b4nuxgd79t1ut32620c8ug07499gc7tg-707f26o0hi-1xdy0o3-n4puiftrn",
					"description": "",
					"type": "text",
					"enabled": true
				},
				{
					"key": "deviceSerial",
					"value": "795616110",
					"description": "",
					"type": "text",
					"enabled": true
				},
				{
					"key": "type",
					"value": "2",
					"description": "声音类型：0-短叫，1-长叫，2-静音",
					"type": "text",
					"enabled": true
				}
			],
			"dataMode": "urlencoded",
			"version": 2,
			"tests": null,
			"currentHelper": "normal",
			"helperAttributes": {},
			"time": 1500879257681,
			"name": "设置报警声音模式",
			"description": "",
			"collectionId": "40f44bf4-aa35-591a-bc4b-d7309a77c866",
			"responses": []
		},
		{
			"id": "f980589a-df36-3146-b9d6-7a03c404d8d6",
			"headers": "Content-Type: application/x-www-form-urlencoded\n",
			"headerData": [
				{
					"key": "Content-Type",
					"value": "application/x-www-form-urlencoded",
					"description": "",
					"enabled": true
				}
			],
			"url": "https://open.ys7.com/api/lapp/device/upgrade",
			"queryParams": [],
			"preRequestScript": null,
			"pathVariables": {},
			"pathVariableData": [],
			"method": "POST",
			"data": [
				{
					"key": "accessToken",
					"value": "at.b4nuxgd79t1ut32620c8ug07499gc7tg-707f26o0hi-1xdy0o3-n4puiftrn",
					"description": "",
					"type": "text",
					"enabled": true
				},
				{
					"key": "deviceSerial",
					"value": "795616110",
					"description": "",
					"type": "text",
					"enabled": true
				}
			],
			"dataMode": "urlencoded",
			"tests": null,
			"currentHelper": "normal",
			"helperAttributes": {},
			"time": 1500878230468,
			"name": "设备升级固件",
			"description": "",
			"collectionId": "40f44bf4-aa35-591a-bc4b-d7309a77c866",
			"responses": []
		},
		{
			"id": "fa190de9-a69e-bf72-389c-fc5643d94cf1",
			"headers": "Content-Type: application/x-www-form-urlencoded\n",
			"headerData": [
				{
					"key": "Content-Type",
					"value": "application/x-www-form-urlencoded",
					"description": "",
					"enabled": true
				}
			],
			"url": "https://open.ys7.com/api/lapp/detector/name/change",
			"queryParams": [],
			"preRequestScript": null,
			"pathVariables": {},
			"pathVariableData": [],
			"method": "POST",
			"data": [
				{
					"key": "accessToken",
					"value": "at.b4nuxgd79t1ut32620c8ug07499gc7tg-707f26o0hi-1xdy0o3-n4puiftrn",
					"description": "",
					"type": "text",
					"enabled": true
				},
				{
					"key": "deviceSerial",
					"value": "795616110",
					"description": "",
					"type": "text",
					"enabled": true
				},
				{
					"key": "detectorSerial",
					"value": "797761167",
					"description": "探测器序列号",
					"type": "text",
					"enabled": true
				},
				{
					"key": "newName",
					"value": "zen-遥控器",
					"description": "新名称，长度不大于50且不包含特殊字符",
					"type": "text",
					"enabled": true
				}
			],
			"dataMode": "urlencoded",
			"tests": null,
			"currentHelper": "normal",
			"helperAttributes": {},
			"time": 1500879252753,
			"name": "改探测器名称",
			"description": "",
			"collectionId": "40f44bf4-aa35-591a-bc4b-d7309a77c866",
			"responses": []
		},
		{
			"id": "fd69ece9-aec9-a391-0856-0f223b92d88f",
			"headers": "Content-Type: application/x-www-form-urlencoded\n",
			"headerData": [
				{
					"key": "Content-Type",
					"value": "application/x-www-form-urlencoded",
					"description": "",
					"enabled": true
				}
			],
			"url": "https://open.ys7.com/api/lapp/detector/delete",
			"queryParams": [],
			"preRequestScript": null,
			"pathVariables": {},
			"pathVariableData": [],
			"method": "POST",
			"data": [
				{
					"key": "accessToken",
					"value": "at.b4nuxgd79t1ut32620c8ug07499gc7tg-707f26o0hi-1xdy0o3-n4puiftrn",
					"description": "",
					"type": "text",
					"enabled": true
				},
				{
					"key": "deviceSerial",
					"value": "795616110",
					"description": "设备序列号",
					"type": "text",
					"enabled": true
				},
				{
					"key": "detectorSerial",
					"value": "795616110",
					"description": "探测器序列号",
					"type": "text",
					"enabled": true
				}
			],
			"dataMode": "urlencoded",
			"tests": null,
			"currentHelper": "normal",
			"helperAttributes": {},
			"time": 1500879254273,
			"name": "删除探测器",
			"description": "",
			"collectionId": "40f44bf4-aa35-591a-bc4b-d7309a77c866",
			"responses": []
		}
	]
}